[{"title":"Meta Quest","link":"com.oculus.twilight","meta":{"image":"https://play-lh.googleusercontent.com/TtK35FoW6K5NE1dJqe1oj0N4ipJIJNdIk9jhe-2G0UEAdWNa1bWB5tdcfm4eQ2fXjA=s180","category":"Entertainment","rank":49,"reviews":39247,"velocity":3}},{"title":"﻿Patreon","link":"com.patreon.android","meta":{"image":"https://play-lh.googleusercontent.com/mGb9igccuINK7_E25XepzEsGDW9aHve8-dLA786yuC4q93tn-WPnuI8ARz4DnfsVFf4=s180","category":"Entertainment","rank":88,"reviews":86635,"velocity":-13}},{"title":"Xfinity Stream","link":"com.xfinity.cloudtvr","meta":{"image":"https://play-lh.googleusercontent.com/3zFRscWd8bdwQJv1aNCqADoMgGydVRTViYpWlX8QPn84t7-z8oU9dIGzJTVrOJQU3Q8=s180","category":"Entertainment","rank":131,"reviews":91204,"velocity":9}},{"title":"Samsung TV Plus-Live TV&Movies","link":"com.samsung.android.tvplus","meta":{"image":"https://play-lh.googleusercontent.com/tOWejMUdWACgAgMadToZDzzxMWTnSV8a3b4znyAv0yHaP2yz-iPw3lKIPagLCSWYxkI=s180","category":"Entertainment","rank":186,"reviews":8983,"velocity":-17}},{"title":"DIRECTV","link":"com.att.tv","meta":{"image":"https://play-lh.googleusercontent.com/BwW5hCoHEuBtzERVYerHWc8twPf_m58Ppf3xptV_N4CuL44QF75hNsBAbC_OARieR7Es=s180","category":"Entertainment","rank":75,"reviews":42819,"velocity":-1}},{"title":"VIZIO Mobile","link":"com.vizio.vue.launcher","meta":{"image":"https://play-lh.googleusercontent.com/t7rZ82H7INT5SmsTuH1-RZ-6iWfhKbhtitufEVey7fELm-TJx5LdDcm3sQINXWMNbdVc=s180","category":"Entertainment","rank":58,"reviews":60364,"velocity":1}},{"title":"Habit Gift","link":"com.habit.step.money.water.sweat.now.tracker","meta":{"image":"https://play-lh.googleusercontent.com/4vRQQBe1MWhXA-Du0fW3NAt79R-Q4aTODgsS26wWaCmAbS5KPPD5nCbsgNYlhQZqBl0=s180","category":"Entertainment","rank":68,"reviews":11074,"velocity":-6}},{"title":"CA Lottery Official App","link":"gov.ca.lot.caLotteryApp","meta":{"image":"https://play-lh.googleusercontent.com/cAOoz9tjFmFKYURWaAbmsLR2qAhyxO4Ql1i-EQP4c9_oek6NV8BKow2sxM2hDC4yUXjA=s180","category":"Entertainment","rank":87,"reviews":23999,"velocity":-1}},{"title":"PlayWell - Play & Earn Rewards","link":"com.play.well.earn.reward.free.income.cash.win.real.money","meta":{"image":"https://play-lh.googleusercontent.com/1DfUB1vPayIhgoecSzPm8Dda3sdAGyMP4XBJfFGXlfD6-unSn8_91y3IxDBYz2jckX5C=s180","category":"Entertainment","rank":24,"reviews":49467,"velocity":-2}},{"title":"Regal: Movie Tickets & Times","link":"com.fandango.regal","meta":{"image":"https://play-lh.googleusercontent.com/3s5-gaFo285S_LjOeeXnl77Rujg55_wgXAODboib2TZgJNbo-1TMjE_cJ8SIIhIy29T1=s180","category":"Entertainment","rank":130,"reviews":44213,"velocity":3}},{"title":"Texas Lottery Official App","link":"com.texas.lottery","meta":{"image":"https://play-lh.googleusercontent.com/hnMbu1GMlaOd75Uf82N4STjpBxTYORVpGHzzhtqYKpeO35n4tzYgBQz79LzzsjJxqG0M=s180","category":"Entertainment","rank":103,"reviews":45408,"velocity":-13}},{"title":"PLAYTIME - Earn Money Playing","link":"pro.cashtree","meta":{"image":"https://play-lh.googleusercontent.com/OYlw2Doh-5n8MZmnDcwu4ytVwUfxNqA3eS_Xx-huPr8zc8WRVlFquXjjb4MGwwH3Gg=s180","category":"Entertainment","rank":72,"reviews":29551,"velocity":-3}},{"title":"T-Mobile Play","link":"com.tmobile.m1","meta":{"image":"https://play-lh.googleusercontent.com/9s9uI5p0P2UEb_t5LBAnincN0BTYb3CsRfHII3s2BQI2sBJlA0DDCfjPdZfo94d1tvc=s180","category":"Entertainment","rank":521,"reviews":15079,"velocity":-66}},{"title":"Sling TV: Live TV + Freestream","link":"com.sling","meta":{"image":"https://play-lh.googleusercontent.com/paUnk-CcCLS-AvbzZw7xdVGU8hpYqRvn_y7aI3r1WMbsW2oCXezFE15Rf4dQgqr3nYe2=s180","category":"Entertainment","rank":34,"reviews":88008,"velocity":10}}]